setup.py
Voice.egg-info/PKG-INFO
Voice.egg-info/SOURCES.txt
Voice.egg-info/dependency_links.txt
Voice.egg-info/not-zip-safe
Voice.egg-info/requires.txt
Voice.egg-info/top_level.txt
example_project/__init__.py
example_project/manage.py
example_project/settings.py
example_project/urls.py
voice/__init__.py
voice/admin.py
voice/forms.py
voice/models.py
voice/settings.py
voice/tests.py
voice/urls.py
voice/views.py
voice/migrations/0001_initial.py
voice/migrations/0002_auto__add_unique_vote_voter_request.py
voice/migrations/0003_auto__del_request__add_feature__del_field_vote_request__add_field_vote.py
voice/migrations/__init__.py
voice/templatetags/__init__.py
voice/templatetags/feature_extras.py