Metadata-Version: 1.0
Name: Voice
Version: 0.1.0
Summary: A voting app for letting users request features.
Home-page: http://github.com/jarodl/voice
Author: Jarod Luebbert
Author-email: jarodluebbert@gmail.com
License: UNKNOWN
Platform: UNKNOWN
Classifier: Framework :: Django
Classifier: Intended Audience :: Developers
Classifier: Intended Audience :: End Users/Desktop
Classifier: Operating System :: OS Independent
